odoo/addons/account_invoice_report_salesperson/README.rst
odoo/addons/account_invoice_report_salesperson/__init__.py
odoo/addons/account_invoice_report_salesperson/__manifest__.py
odoo/addons/account_invoice_report_salesperson/i18n/account_invoice_report_salesperson.pot
odoo/addons/account_invoice_report_salesperson/i18n/ca.po
odoo/addons/account_invoice_report_salesperson/i18n/ca_ES.po
odoo/addons/account_invoice_report_salesperson/i18n/es.po
odoo/addons/account_invoice_report_salesperson/i18n/it.po
odoo/addons/account_invoice_report_salesperson/readme/CONTRIBUTORS.md
odoo/addons/account_invoice_report_salesperson/readme/DESCRIPTION.md
odoo/addons/account_invoice_report_salesperson/readme/USAGE.md
odoo/addons/account_invoice_report_salesperson/static/description/icon.png
odoo/addons/account_invoice_report_salesperson/static/description/index.html
odoo/addons/account_invoice_report_salesperson/views/report_invoice.xml
odoo_addon_account_invoice_report_salesperson-16.0.1.0.1.5.dist-info/METADATA
odoo_addon_account_invoice_report_salesperson-16.0.1.0.1.5.dist-info/WHEEL
odoo_addon_account_invoice_report_salesperson-16.0.1.0.1.5.dist-info/top_level.txt
odoo_addon_account_invoice_report_salesperson-16.0.1.0.1.5.dist-info/RECORD
