Metadata-Version: 2.1
Name: odoo-addon-account_invoice_report_salesperson
Version: 16.0.1.0.1.5
Summary: Salesperson info in Invoice report
Home-page: https://github.com/OCA/account-invoice-reporting
Author: Moduon, Odoo Community Association (OCA)
Author-email: support@odoo-community.org
License: LGPL-3
Classifier: Programming Language :: Python
Classifier: Framework :: Odoo
Classifier: Framework :: Odoo :: 16.0
Classifier: License :: OSI Approved :: GNU Lesser General Public License v3 (LGPLv3)
Classifier: Development Status :: 3 - Alpha
Requires-Python: >=3.10
Requires-Dist: odoo<16.1dev,>=16.0a
